CHANGELOG.txt
LICENCE.txt
MANIFEST.in
README.txt
main.py
setup.cfg
setup.py
ravin/__init__.py
ravin/iot_dp.py
ravin/my_testfuns.py
ravin.egg-info/PKG-INFO
ravin.egg-info/SOURCES.txt
ravin.egg-info/dependency_links.txt
ravin.egg-info/requires.txt
ravin.egg-info/top_level.txt