Metadata-Version: 1.1
Name: ravin
Version: 1.0.0
Summary: Optimize the power consumption of any IoT deployment using a single line of code.
Home-page: UNKNOWN
Author: Vineet Dhaimodker
Author-email: thevineet44@gmail.com
License: MIT
Download-URL: https://github.com/Vineet-Dhaimodker/ravin/archive/v1.0.0.tar.gz
Keywords: Iot,Power,Optimization,Energy,Dynamic Programming
Platform: UNKNOWN
Classifier: Development Status :: 5 - Production/Stable
Classifier: Intended Audience :: Education
Classifier: Topic :: Software Development :: Build Tools
Classifier: License :: OSI Approved :: MIT License
Classifier: Operating System :: Microsoft :: Windows :: Windows 10
Classifier: Programming Language :: Python :: 3
